repoze.errorlog-1.1-py2.7-nspkg.pth
repoze/errorlog/__init__.py
repoze/errorlog/_compat.py
repoze/errorlog/tests.py
repoze/errorlog/templates/entry.html
repoze/errorlog/templates/errors.html
repoze.errorlog-1.1.dist-info/DESCRIPTION.rst
repoze.errorlog-1.1.dist-info/METADATA
repoze.errorlog-1.1.dist-info/RECORD
repoze.errorlog-1.1.dist-info/WHEEL
repoze.errorlog-1.1.dist-info/entry_points.txt
repoze.errorlog-1.1.dist-info/metadata.json
repoze.errorlog-1.1.dist-info/namespace_packages.txt
repoze.errorlog-1.1.dist-info/top_level.txt
